jupyter_mcp_servers/__init__.py
jupyter_mcp_servers/__main__.py
jupyter_mcp_servers/_version.py
jupyter_mcp_servers/application.py
jupyter_mcp_servers/serverapplication.py
jupyter_mcp_servers/handlers/__init__.py
jupyter_mcp_servers/handlers/base.py
jupyter_mcp_servers/handlers/config/__init__.py
jupyter_mcp_servers/handlers/config/handler.py
jupyter_mcp_servers/handlers/index/__init__.py
jupyter_mcp_servers/handlers/index/handler.py
jupyter_mcp_servers/static/README.md
jupyter_mcp_servers/static/main.jupyter-mcp-servers.js
jupyter_mcp_servers/templates/index.html
jupyter_mcp_servers/tests/__init__.py
jupyter_mcp_servers/tests/test_handlers.py
jupyter_mcp_servers-1.2.16.data/data/etc/jupyter/jupyter_notebook_config.d/jupyter_kernels.json
jupyter_mcp_servers-1.2.16.data/data/etc/jupyter/jupyter_server_config.d/jupyter_kernels.json
jupyter_mcp_servers-1.2.16.data/data/share/jupyter/labextensions/@datalayer/jupyter-mcp-servers/package.json
jupyter_mcp_servers-1.2.16.data/data/share/jupyter/labextensions/@datalayer/jupyter-mcp-servers/schemas/@datalayer/jupyter-mcp-servers/package.json.orig
jupyter_mcp_servers-1.2.16.data/data/share/jupyter/labextensions/@datalayer/jupyter-mcp-servers/schemas/@datalayer/jupyter-mcp-servers/plugin.json
jupyter_mcp_servers-1.2.16.data/data/share/jupyter/labextensions/@datalayer/jupyter-mcp-servers/static/205.75f84821ca9b2a44acae.js
jupyter_mcp_servers-1.2.16.data/data/share/jupyter/labextensions/@datalayer/jupyter-mcp-servers/static/568.57816cce3395ca304332.js
jupyter_mcp_servers-1.2.16.data/data/share/jupyter/labextensions/@datalayer/jupyter-mcp-servers/static/776.92a5d432f3dc36218178.js
jupyter_mcp_servers-1.2.16.data/data/share/jupyter/labextensions/@datalayer/jupyter-mcp-servers/static/remoteEntry.ad8f927368c7f1f30bf7.js
jupyter_mcp_servers-1.2.16.data/data/share/jupyter/labextensions/@datalayer/jupyter-mcp-servers/static/style.js
jupyter_mcp_servers-1.2.16.dist-info/METADATA
jupyter_mcp_servers-1.2.16.dist-info/WHEEL
jupyter_mcp_servers-1.2.16.dist-info/entry_points.txt
jupyter_mcp_servers-1.2.16.dist-info/licenses/LICENSE
jupyter_mcp_servers-1.2.16.dist-info/RECORD
