Metadata-Version: 2.1
Name: jupyter_mcp_servers
Version: 1.2.16
Summary: 🪐 ✨ Jupyter MCP Servers.
Project-URL: Homepage, https://github.com/datalayer/jupyter-mcp-servers
Project-URL: Bug Tracker, https://github.com/datalayer/jupyter-mcp-servers/issues
Project-URL: Repository, https://github.com/datalayer/jupyter-mcp-servers.git
Author-email: Datalayer <info@datalayer.io>
License: Datalayer License
License-File: LICENSE
Classifier: Framework :: Jupyter
Classifier: Framework :: Jupyter :: JupyterLab
Classifier: Framework :: Jupyter :: JupyterLab :: 4
Classifier: Framework :: Jupyter :: JupyterLab :: Extensions
Classifier: Framework :: Jupyter :: JupyterLab :: Extensions :: Prebuilt
Classifier: Intended Audience :: Developers
Classifier: Intended Audience :: Science/Research
Classifier: Intended Audience :: System Administrators
Classifier: Programming Language :: Python
Classifier: Programming Language :: Python :: 3
Classifier: Programming Language :: Python :: 3.9
Classifier: Programming Language :: Python :: 3.10
Classifier: Programming Language :: Python :: 3.11
Classifier: Programming Language :: Python :: 3.12
Requires-Python: >=3.9
Requires-Dist: datalayer-core>=1.0.0
Requires-Dist: jupyter-client>=8.6.0
Requires-Dist: jupyter-console
Requires-Dist: jupyter-iam
Requires-Dist: jupyter-server<3,>=2.10
Requires-Dist: keyring
Requires-Dist: prompt-toolkit>=3.0.0
Requires-Dist: questionary>=2
Requires-Dist: requests
Requires-Dist: rich
Requires-Dist: websocket-client
Provides-Extra: test
Requires-Dist: coverage; extra == 'test'
Requires-Dist: pytest; extra == 'test'
Requires-Dist: pytest-asyncio; extra == 'test'
Requires-Dist: pytest-cov; extra == 'test'
Requires-Dist: pytest-jupyter; extra == 'test'
Requires-Dist: pytest-tornasync; extra == 'test'
